<annotation>
  <folder>20210526</folder>
  <filename>20210526_06_48_00_000_cRZBBnhaTifVuUVCwVT7NBQaZYq2_F_4000_3000.jpg</filename>
  <source>
    <database>Unknown</database>
    <annotation>Unknown</annotation>
    <image>Unknown</image>
  </source>
  <size>
    <width>3000</width>
    <height>4000</height>
    <depth></depth>
  </size>
  <segmented>0</segmented>
  <object>
    <name>two_wheelers</name>
    <truncated>0</truncated>
    <occluded>0</occluded>
    <difficult>0</difficult>
    <bndbox>
      <xmin>525.08</xmin>
      <ymin>1703.39</ymin>
      <xmax>864.2</xmax>
      <ymax>2005.58</ymax>
    </bndbox>
    <attributes>
      <attribute>
        <name>rotation</name>
        <value>0.0</value>
      </attribute>
    </attributes>
  </object>
  <object>
    <name>bus</name>
    <truncated>0</truncated>
    <occluded>0</occluded>
    <difficult>0</difficult>
    <bndbox>
      <xmin>898.92</xmin>
      <ymin>1291.29</ymin>
      <xmax>1751.89</xmax>
      <ymax>1883.49</ymax>
    </bndbox>
    <attributes>
      <attribute>
        <name>rotation</name>
        <value>0.0</value>
      </attribute>
    </attributes>
  </object>
  <object>
    <name>two_wheelers</name>
    <truncated>0</truncated>
    <occluded>0</occluded>
    <difficult>0</difficult>
    <bndbox>
      <xmin>939.63</xmin>
      <ymin>1713.34</ymin>
      <xmax>1261.19</xmax>
      <ymax>2051.82</ymax>
    </bndbox>
    <attributes>
      <attribute>
        <name>rotation</name>
        <value>0.0</value>
      </attribute>
    </attributes>
  </object>
</annotation>
