<annotation>
  <folder></folder>
  <filename>Datacluster Auto (96).jpg</filename>
  <source>
    <database>Unknown</database>
    <annotation>Unknown</annotation>
    <image>Unknown</image>
  </source>
  <size>
    <width>1536</width>
    <height>2048</height>
    <depth></depth>
  </size>
  <segmented>0</segmented>
  <object>
    <name>tempo</name>
    <truncated>0</truncated>
    <occluded>0</occluded>
    <difficult>0</difficult>
    <bndbox>
      <xmin>0.78</xmin>
      <ymin>562.29</ymin>
      <xmax>157.52</xmax>
      <ymax>773.76</ymax>
    </bndbox>
    <attributes>
      <attribute>
        <name>rotation</name>
        <value>0.0</value>
      </attribute>
    </attributes>
  </object>
  <object>
    <name>two_wheelers</name>
    <truncated>0</truncated>
    <occluded>0</occluded>
    <difficult>0</difficult>
    <bndbox>
      <xmin>110.56</xmin>
      <ymin>619.26</ymin>
      <xmax>253.33</xmax>
      <ymax>786.03</ymax>
    </bndbox>
    <attributes>
      <attribute>
        <name>rotation</name>
        <value>0.0</value>
      </attribute>
    </attributes>
  </object>
  <object>
    <name>two_wheelers</name>
    <truncated>0</truncated>
    <occluded>0</occluded>
    <difficult>0</difficult>
    <bndbox>
      <xmin>432.1</xmin>
      <ymin>632.46</ymin>
      <xmax>763.23</xmax>
      <ymax>800.43</ymax>
    </bndbox>
    <attributes>
      <attribute>
        <name>rotation</name>
        <value>0.0</value>
      </attribute>
    </attributes>
  </object>
  <object>
    <name>car</name>
    <truncated>0</truncated>
    <occluded>0</occluded>
    <difficult>0</difficult>
    <bndbox>
      <xmin>1048.8</xmin>
      <ymin>538.88</ymin>
      <xmax>1144.76</xmax>
      <ymax>606.06</ymax>
    </bndbox>
    <attributes>
      <attribute>
        <name>rotation</name>
        <value>0.0</value>
      </attribute>
    </attributes>
  </object>
  <object>
    <name>car</name>
    <truncated>0</truncated>
    <occluded>0</occluded>
    <difficult>0</difficult>
    <bndbox>
      <xmin>1240.74</xmin>
      <ymin>496.88</ymin>
      <xmax>1389.52</xmax>
      <ymax>615.66</ymax>
    </bndbox>
    <attributes>
      <attribute>
        <name>rotation</name>
        <value>0.0</value>
      </attribute>
    </attributes>
  </object>
  <object>
    <name>auto</name>
    <truncated>0</truncated>
    <occluded>0</occluded>
    <difficult>0</difficult>
    <bndbox>
      <xmin>283.32</xmin>
      <ymin>613.26</ymin>
      <xmax>374.51</xmax>
      <ymax>700.85</ymax>
    </bndbox>
    <attributes>
      <attribute>
        <name>rotation</name>
        <value>0.0</value>
      </attribute>
    </attributes>
  </object>
  <object>
    <name>auto</name>
    <truncated>0</truncated>
    <occluded>0</occluded>
    <difficult>0</difficult>
    <bndbox>
      <xmin>405.7</xmin>
      <ymin>552.07</ymin>
      <xmax>508.88</xmax>
      <ymax>703.25</ymax>
    </bndbox>
    <attributes>
      <attribute>
        <name>rotation</name>
        <value>0.0</value>
      </attribute>
    </attributes>
  </object>
  <object>
    <name>auto</name>
    <truncated>0</truncated>
    <occluded>0</occluded>
    <difficult>0</difficult>
    <bndbox>
      <xmin>508.88</xmin>
      <ymin>541.28</ymin>
      <xmax>610.86</xmax>
      <ymax>660.05</ymax>
    </bndbox>
    <attributes>
      <attribute>
        <name>rotation</name>
        <value>0.0</value>
      </attribute>
    </attributes>
  </object>
</annotation>
